usps/__init__.py
usps/address.py
usps/constants.py
usps/tests.py
usps/usps.py
usps_api-0.3.dist-info/LICENSE
usps_api-0.3.dist-info/METADATA
usps_api-0.3.dist-info/WHEEL
usps_api-0.3.dist-info/top_level.txt
usps_api-0.3.dist-info/RECORD
