Metadata-Version: 1.1
Name: usps-api
Version: 0.3
Summary: Python wrapper for the USPS API
Home-page: http://github.com/brobin/usps-api
Author: Tobin Brown
Author-email: tobin@brobin.me
License: MIT
Keywords: usps shipping
Platform: UNKNOWN
Classifier: Development Status :: 3 - Alpha
Classifier: Intended Audience :: Information Technology
Classifier: License :: OSI Approved :: MIT License
Classifier: Natural Language :: English
Classifier: Programming Language :: Python
Classifier: Programming Language :: Python :: 3
Classifier: Programming Language :: Python :: 3.4
Classifier: Programming Language :: Python :: 3.5
Classifier: Programming Language :: Python :: 3.6
Classifier: Topic :: Software Development :: Libraries :: Python Modules
Classifier: Topic :: Software Development :: Testing
Classifier: Topic :: Utilities
